{
  "run": {
    "command": "nx build admin-portal --skip-nx-cache",
    "startTime": "2026-06-18T07:10:32.888Z",
    "endTime": "2026-06-18T07:10:49.014Z",
    "inner": false
  },
  "tasks": [
    {
      "taskId": "admin-portal:build:production",
      "target": "build",
      "projectName": "admin-portal",
      "hash": "18388878913461291980",
      "startTime": "2026-06-18T07:10:32.907Z",
      "endTime": "2026-06-18T07:10:48.994Z",
      "params": "",
      "cacheStatus": "cache-miss",
      "status": 0
    }
  ]
}